{
    "1": {
        "id": 1, 
        "single": "2209|812"
    }, 
    "2": {
        "id": 2, 
        "single": "2209|650"
    }, 
    "3": {
        "id": 3, 
        "single": "2209|568"
    }, 
    "4": {
        "id": 4, 
        "single": "2209|552"
    }, 
    "5": {
        "id": 5, 
        "single": "2209|536"
    }, 
    "6": {
        "id": 6, 
        "single": "2209|520"
    }, 
    "7": {
        "id": 7, 
        "single": "2209|503"
    }, 
    "8": {
        "id": 8, 
        "single": "2209|487"
    }, 
    "9": {
        "id": 9, 
        "single": "2209|471"
    }, 
    "10": {
        "id": 10, 
        "single": "2209|455"
    }, 
    "11": {
        "id": 11, 
        "single": "2209|438"
    }, 
    "12": {
        "id": 12, 
        "single": "2209|422"
    }, 
    "13": {
        "id": 13, 
        "single": "2209|406"
    }, 
    "14": {
        "id": 14, 
        "single": "2209|390"
    }, 
    "15": {
        "id": 15, 
        "single": "2209|373"
    }, 
    "16": {
        "id": 16, 
        "single": "2209|357"
    }, 
    "17": {
        "id": 17, 
        "single": "2209|341"
    }, 
    "18": {
        "id": 18, 
        "single": "2209|325"
    }, 
    "19": {
        "id": 19, 
        "single": "2209|308"
    }, 
    "20": {
        "id": 20, 
        "single": "2209|292"
    }, 
    "21": {
        "id": 21, 
        "single": "2209|250"
    }, 
    "22": {
        "id": 22, 
        "single": "2209|243"
    }, 
    "23": {
        "id": 23, 
        "single": "2209|237"
    }, 
    "24": {
        "id": 24, 
        "single": "2209|230"
    }, 
    "25": {
        "id": 25, 
        "single": "2209|223"
    }, 
    "26": {
        "id": 26, 
        "single": "2209|216"
    }, 
    "27": {
        "id": 27, 
        "single": "2209|209"
    }, 
    "28": {
        "id": 28, 
        "single": "2209|203"
    }, 
    "29": {
        "id": 29, 
        "single": "2209|196"
    }, 
    "30": {
        "id": 30, 
        "single": "2209|189"
    }, 
    "31": {
        "id": 31, 
        "single": "2209|186"
    }, 
    "32": {
        "id": 32, 
        "single": "2209|184"
    }, 
    "33": {
        "id": 33, 
        "single": "2209|181"
    }, 
    "34": {
        "id": 34, 
        "single": "2209|178"
    }, 
    "35": {
        "id": 35, 
        "single": "2209|176"
    }, 
    "36": {
        "id": 36, 
        "single": "2209|173"
    }, 
    "37": {
        "id": 37, 
        "single": "2209|170"
    }, 
    "38": {
        "id": 38, 
        "single": "2209|168"
    }, 
    "39": {
        "id": 39, 
        "single": "2209|165"
    }, 
    "40": {
        "id": 40, 
        "single": "2209|162"
    }, 
    "41": {
        "id": 41, 
        "single": "2209|159"
    }, 
    "42": {
        "id": 42, 
        "single": "2209|157"
    }, 
    "43": {
        "id": 43, 
        "single": "2209|154"
    }, 
    "44": {
        "id": 44, 
        "single": "2209|151"
    }, 
    "45": {
        "id": 45, 
        "single": "2209|149"
    }, 
    "46": {
        "id": 46, 
        "single": "2209|146"
    }, 
    "47": {
        "id": 47, 
        "single": "2209|143"
    }, 
    "48": {
        "id": 48, 
        "single": "2209|140"
    }, 
    "49": {
        "id": 49, 
        "single": "2209|138"
    }, 
    "50": {
        "id": 50, 
        "single": "2209|135"
    }, 
    "51": {
        "id": 51, 
        "single": "2209|108"
    }, 
    "52": {
        "id": 52, 
        "single": "2209|107"
    }, 
    "53": {
        "id": 53, 
        "single": "2209|105"
    }, 
    "54": {
        "id": 54, 
        "single": "2209|104"
    }, 
    "55": {
        "id": 55, 
        "single": "2209|103"
    }, 
    "56": {
        "id": 56, 
        "single": "2209|101"
    }, 
    "57": {
        "id": 57, 
        "single": "2209|100"
    }, 
    "58": {
        "id": 58, 
        "single": "2209|98"
    }, 
    "59": {
        "id": 59, 
        "single": "2209|97"
    }, 
    "60": {
        "id": 60, 
        "single": "2209|96"
    }, 
    "61": {
        "id": 61, 
        "single": "2209|94"
    }, 
    "62": {
        "id": 62, 
        "single": "2209|93"
    }, 
    "63": {
        "id": 63, 
        "single": "2209|92"
    }, 
    "64": {
        "id": 64, 
        "single": "2209|90"
    }, 
    "65": {
        "id": 65, 
        "single": "2209|89"
    }, 
    "66": {
        "id": 66, 
        "single": "2209|75"
    }, 
    "67": {
        "id": 67, 
        "single": "2209|75"
    }, 
    "68": {
        "id": 68, 
        "single": "2209|74"
    }, 
    "69": {
        "id": 69, 
        "single": "2209|73"
    }, 
    "70": {
        "id": 70, 
        "single": "2209|73"
    }, 
    "71": {
        "id": 71, 
        "single": "2209|72"
    }, 
    "72": {
        "id": 72, 
        "single": "2209|71"
    }, 
    "73": {
        "id": 73, 
        "single": "2209|71"
    }, 
    "74": {
        "id": 74, 
        "single": "2209|70"
    }, 
    "75": {
        "id": 75, 
        "single": "2209|69"
    }, 
    "76": {
        "id": 76, 
        "single": "2209|69"
    }, 
    "77": {
        "id": 77, 
        "single": "2209|68"
    }, 
    "78": {
        "id": 78, 
        "single": "2209|67"
    }, 
    "79": {
        "id": 79, 
        "single": "2209|67"
    }, 
    "80": {
        "id": 80, 
        "single": "2209|66"
    }, 
    "81": {
        "id": 81, 
        "single": "2209|65"
    }, 
    "82": {
        "id": 82, 
        "single": "2209|65"
    }, 
    "83": {
        "id": 83, 
        "single": "2209|64"
    }, 
    "84": {
        "id": 84, 
        "single": "2209|63"
    }, 
    "85": {
        "id": 85, 
        "single": "2209|63"
    }, 
    "86": {
        "id": 86, 
        "single": "2209|62"
    }, 
    "87": {
        "id": 87, 
        "single": "2209|61"
    }, 
    "88": {
        "id": 88, 
        "single": "2209|60"
    }, 
    "89": {
        "id": 89, 
        "single": "2209|60"
    }, 
    "90": {
        "id": 90, 
        "single": "2209|59"
    }, 
    "91": {
        "id": 91, 
        "single": "2209|54"
    }, 
    "92": {
        "id": 92, 
        "single": "2209|52"
    }, 
    "93": {
        "id": 93, 
        "single": "2209|51"
    }, 
    "94": {
        "id": 94, 
        "single": "2209|50"
    }, 
    "95": {
        "id": 95, 
        "single": "2209|48"
    }, 
    "96": {
        "id": 96, 
        "single": "2209|47"
    }, 
    "97": {
        "id": 97, 
        "single": "2209|46"
    }, 
    "98": {
        "id": 98, 
        "single": "2209|44"
    }, 
    "99": {
        "id": 99, 
        "single": "2209|43"
    }, 
    "100": {
        "id": 100, 
        "single": "2209|42"
    }, 
    "101": {
        "id": 101, 
        "single": "2209|42"
    }, 
    "102": {
        "id": 102, 
        "single": "2209|42"
    }, 
    "103": {
        "id": 103, 
        "single": "2209|42"
    }, 
    "104": {
        "id": 104, 
        "single": "2209|42"
    }, 
    "105": {
        "id": 105, 
        "single": "2209|42"
    }, 
    "106": {
        "id": 106, 
        "single": "2209|42"
    }, 
    "107": {
        "id": 107, 
        "single": "2209|42"
    }, 
    "108": {
        "id": 108, 
        "single": "2209|42"
    }, 
    "109": {
        "id": 109, 
        "single": "2209|42"
    }, 
    "110": {
        "id": 110, 
        "single": "2209|42"
    }, 
    "111": {
        "id": 111, 
        "single": "2209|42"
    }, 
    "112": {
        "id": 112, 
        "single": "2209|42"
    }, 
    "113": {
        "id": 113, 
        "single": "2209|42"
    }, 
    "114": {
        "id": 114, 
        "single": "2209|42"
    }, 
    "115": {
        "id": 115, 
        "single": "2209|42"
    }, 
    "116": {
        "id": 116, 
        "single": "2209|42"
    }, 
    "117": {
        "id": 117, 
        "single": "2209|42"
    }, 
    "118": {
        "id": 118, 
        "single": "2209|42"
    }, 
    "119": {
        "id": 119, 
        "single": "2209|42"
    }, 
    "120": {
        "id": 120, 
        "single": "2209|42"
    }, 
    "121": {
        "id": 121, 
        "single": "2209|42"
    }, 
    "122": {
        "id": 122, 
        "single": "2209|42"
    }, 
    "123": {
        "id": 123, 
        "single": "2209|42"
    }, 
    "124": {
        "id": 124, 
        "single": "2209|42"
    }, 
    "125": {
        "id": 125, 
        "single": "2209|42"
    }, 
    "126": {
        "id": 126, 
        "single": "2209|42"
    }, 
    "127": {
        "id": 127, 
        "single": "2209|42"
    }, 
    "128": {
        "id": 128, 
        "single": "2209|42"
    }, 
    "129": {
        "id": 129, 
        "single": "2209|42"
    }, 
    "130": {
        "id": 130, 
        "single": "2209|42"
    }, 
    "131": {
        "id": 131, 
        "single": "2209|42"
    }, 
    "132": {
        "id": 132, 
        "single": "2209|42"
    }, 
    "133": {
        "id": 133, 
        "single": "2209|42"
    }, 
    "134": {
        "id": 134, 
        "single": "2209|42"
    }, 
    "135": {
        "id": 135, 
        "single": "2209|42"
    }, 
    "136": {
        "id": 136, 
        "single": "2209|42"
    }, 
    "137": {
        "id": 137, 
        "single": "2209|42"
    }, 
    "138": {
        "id": 138, 
        "single": "2209|42"
    }, 
    "139": {
        "id": 139, 
        "single": "2209|42"
    }, 
    "140": {
        "id": 140, 
        "single": "2209|42"
    }, 
    "141": {
        "id": 141, 
        "single": "2209|42"
    }, 
    "142": {
        "id": 142, 
        "single": "2209|42"
    }, 
    "143": {
        "id": 143, 
        "single": "2209|42"
    }, 
    "144": {
        "id": 144, 
        "single": "2209|42"
    }, 
    "145": {
        "id": 145, 
        "single": "2209|42"
    }, 
    "146": {
        "id": 146, 
        "single": "2209|42"
    }, 
    "147": {
        "id": 147, 
        "single": "2209|42"
    }, 
    "148": {
        "id": 148, 
        "single": "2209|42"
    }, 
    "149": {
        "id": 149, 
        "single": "2209|42"
    }, 
    "150": {
        "id": 150, 
        "single": "2209|42"
    }
}